haproxy/__init__.py
haproxy/commands.py
haproxy/filters.py
haproxy/line.py
haproxy/logfile.py
haproxy/main.py
haproxy/utils.py
tests/__init__.py
tests/conftest.py
tests/test_argparse.py
tests/test_commands.py
tests/test_filters.py
tests/test_log_file.py
tests/test_log_line.py
tests/test_main.py
tests/test_regex.py
tests/test_utils.py
tests/files/2_ok_1_invalid.log
tests/files/small.log
haproxy_log_analysis-5.1.0.dist-info/LICENSE
haproxy_log_analysis-5.1.0.dist-info/METADATA
haproxy_log_analysis-5.1.0.dist-info/WHEEL
haproxy_log_analysis-5.1.0.dist-info/entry_points.txt
haproxy_log_analysis-5.1.0.dist-info/top_level.txt
haproxy_log_analysis-5.1.0.dist-info/RECORD
