Metadata-Version: 2.1
Name: haproxy-log-analysis
Version: 5.1.0
Summary: Haproxy log analyzer that tries to gives an insight of what's going on
Home-page: https://github.com/gforcada/haproxy_log_analysis
Author: Gil Forcada
Author-email: gil.gnome@gmail.com
License: GPL v3
Keywords: haproxy log analysis report
Classifier: Development Status :: 5 - Production/Stable
Classifier: Environment :: Console
Classifier: Intended Audience :: System Administrators
Classifier: License :: OSI Approved :: GNU General Public License v3 (GPLv3)
Classifier: Operating System :: OS Independent
Classifier: Programming Language :: Python
Classifier: Programming Language :: Python :: 3
Classifier: Programming Language :: Python :: 3 :: Only
Classifier: Programming Language :: Python :: 3.7
Classifier: Programming Language :: Python :: 3.8
Classifier: Programming Language :: Python :: 3.9
Classifier: Programming Language :: Python :: 3.10
Classifier: Programming Language :: Python :: 3.11
Classifier: Programming Language :: Python :: Implementation :: CPython
Classifier: Programming Language :: Python :: Implementation :: PyPy
Classifier: Topic :: Internet :: Log Analysis
Requires-Python: >=3.7
License-File: LICENSE
Requires-Dist: setuptools
